{
  " ": 0.27,
  "!": 0.27,
  "\"": 0.39,
  "#": 0.60,
  "$": 0.57,
  "%": 0.84,
  "&": 0.68,
  "'": 0.22,
  "(": 0.34,
  ")": 0.34,
  "*": 0.44,
  "+": 0.60,
  ",": 0.25,
  "-": 0.38,
  ".": 0.27,
  "/": 0.34,
  "0": 0.60,
  "1": 0.52,
  "2": 0.57,
  "3": 0.57,
  "4": 0.60,
  "5": 0.57,
  "6": 0.58,
  "7": 0.55,
  "8": 0.58,
  "9": 0.58,
  ":": 0.25,
  ";": 0.25,
  "<": 0.60,
  "=": 0.60,
  ">": 0.60,
  "?": 0.52,
  "@": 0.97,
  "A": 0.68,
  "B": 0.66,
  "C": 0.68,
  "D": 0.72,
  "E": 0.61,
  "F": 0.58,
  "G": 0.73,
  "H": 0.74,
  "I": 0.28,
  "J": 0.51,
  "K": 0.67,
  "L": 0.58,
  "M": 0.88,
  "N": 0.74,
  "O": 0.75,
  "P": 0.64,
  "Q": 0.75,
  "R": 0.67,
  "S": 0.61,
  "T": 0.62,
  "U": 0.72,
  "V": 0.66,
  "W": 0.95,
  "X": 0.64,
  "Y": 0.62,
  "Z": 0.61,
  "[": 0.30,
  "\\": 0.34,
  "]": 0.30,
  "^": 0.52,
  "_": 0.50,
  "`": 0.50,
  "a": 0.56,
  "b": 0.59,
  "c": 0.52,
  "d": 0.59,
  "e": 0.56,
  "f": 0.34,
  "g": 0.59,
  "h": 0.59,
  "i": 0.26,
  "j": 0.26,
  "k": 0.54,
  "l": 0.26,
  "m": 0.89,
  "n": 0.59,
  "o": 0.58,
  "p": 0.59,
  "q": 0.59,
  "r": 0.38,
  "s": 0.50,
  "t": 0.36,
  "u": 0.59,
  "v": 0.52,
  "w": 0.77,
  "x": 0.52,
  "y": 0.52,
  "z": 0.50,
  "{": 0.36,
  "|": 0.28,
  "}": 0.36,
  "~": 0.60
}
